picogen/__init__.py
picogen/__main__.py
picogen/_version.py
picogen/backup.py
picogen/cli.py
picogen/config.py
picogen/deploy.py
picogen/generate.py
picogen/default_theme/static/css/style.css
picogen/default_theme/static/favicons/android-chrome-192x192.png
picogen/default_theme/static/favicons/android-chrome-256x256.png
picogen/default_theme/static/favicons/apple-touch-icon.png
picogen/default_theme/static/favicons/browserconfig.xml
picogen/default_theme/static/favicons/favicon-16x16.png
picogen/default_theme/static/favicons/favicon-32x32.png
picogen/default_theme/static/favicons/favicon.ico
picogen/default_theme/static/favicons/manifest.json
picogen/default_theme/static/favicons/mstile-150x150.png
picogen/default_theme/static/favicons/safari-pinned-tab.svg
picogen/default_theme/static/images/logo.svg
picogen/default_theme/templates/404.html
picogen/default_theme/templates/category.html
picogen/default_theme/templates/home.html
picogen/default_theme/templates/page.html
picogen/default_theme/templates/post.html
picogen/default_theme/templates/robots.txt
picogen/default_theme/templates/sitemap.xml
picogen/default_theme/templates/sitemap.xsl
picogen/default_theme/templates/components/analytics.html
picogen/default_theme/templates/components/base.html
picogen-0.0.25.dist-info/licenses/LICENSE
picogen-0.0.25.dist-info/METADATA
picogen-0.0.25.dist-info/WHEEL
picogen-0.0.25.dist-info/entry_points.txt
picogen-0.0.25.dist-info/top_level.txt
picogen-0.0.25.dist-info/RECORD
