Metadata-Version: 2.4
Name: picogen
Version: 0.0.25
Summary: Minimalist static website generator in Python.
Maintainer: vlatan
License-Expression: MIT
Project-URL: Homepage, https://github.com/vlatan/picogen
Classifier: Programming Language :: Python :: 3
Classifier: Operating System :: OS Independent
Classifier: Intended Audience :: End Users/Desktop
Classifier: Environment :: Console
Classifier: Topic :: Internet :: WWW/HTTP :: Dynamic Content :: Content Management System
Classifier: Topic :: Internet :: WWW/HTTP :: Site Management
Classifier: Topic :: Software Development :: Libraries :: Python Modules
Classifier: Topic :: Text Processing :: Markup :: Markdown
Classifier: Topic :: Text Processing :: Markup :: HTML
Requires-Python: >=3.8
License-File: LICENSE
Requires-Dist: beautifulsoup4==4.12.3
Requires-Dist: Jinja2==3.1.4
Requires-Dist: Markdown==3.6
Requires-Dist: Pygments==2.18.0
Requires-Dist: python-dotenv==1.0.1
Requires-Dist: python-slugify==8.0.4
Provides-Extra: dev
Requires-Dist: pytest==8.3.2; extra == "dev"
Requires-Dist: black==24.4.2; extra == "dev"
Dynamic: license-file
